graficombustion/__init__.py
graficombustion/plotter.py
graficombustion-0.2.0.dist-info/licenses/LICENSE
graficombustion-0.2.0.dist-info/METADATA
graficombustion-0.2.0.dist-info/WHEEL
graficombustion-0.2.0.dist-info/top_level.txt
graficombustion-0.2.0.dist-info/RECORD
