Metadata-Version: 2.4
Name: graficombustion
Version: 0.2.0
Summary: Una librería para generar gráficos de los resultados de las simulaciones de simcombustion.
Author-email: Tu Nombre <tu@email.com>
Classifier: Programming Language :: Python :: 3
Classifier: License :: OSI Approved :: MIT License
Classifier: Operating System :: OS Independent
Classifier: Topic :: Scientific/Engineering :: Visualization
Requires-Python: >=3.8
License-File: LICENSE
Requires-Dist: simcombustion>=0.1.0
Requires-Dist: matplotlib
Requires-Dist: numpy
Dynamic: license-file
